django_aws_xray/__init__.py
django_aws_xray/apps.py
django_aws_xray/connection.py
django_aws_xray/middleware.py
django_aws_xray/records.py
django_aws_xray/traces.py
django_aws_xray/xray.py
django_aws_xray/patches/__init__.py
django_aws_xray/patches/cache.py
django_aws_xray/patches/db.py
django_aws_xray/patches/redis.py
django_aws_xray/patches/requests.py
django_aws_xray/patches/templates.py
django_aws_xray/patches/utils.py
django_aws_xray-0.2.2.dist-info/DESCRIPTION.rst
django_aws_xray-0.2.2.dist-info/METADATA
django_aws_xray-0.2.2.dist-info/RECORD
django_aws_xray-0.2.2.dist-info/WHEEL
django_aws_xray-0.2.2.dist-info/metadata.json
django_aws_xray-0.2.2.dist-info/top_level.txt
