Metadata-Version: 2.0
Name: django-aws-xray
Version: 0.2.2
Summary: Django AWS X-Ray
Home-page: https://github.com/mvantellingen/django-aws-xray
Author: Michael van Tellingen
Author-email: UNKNOWN
License: MIT
Platform: UNKNOWN
Classifier: Development Status :: 5 - Production/Stable
Classifier: Environment :: Web Environment
Classifier: Framework :: Django
Classifier: Framework :: Django :: 1.11
Classifier: License :: OSI Approved :: MIT License
Classifier: Programming Language :: Python
Classifier: Programming Language :: Python :: 3
Classifier: Programming Language :: Python :: 3.4
Classifier: Programming Language :: Python :: 3.5
Classifier: Programming Language :: Python :: 3.6
Requires-Dist: Django (>=1.8)
Requires-Dist: attrs (>=17.2.0)
Requires-Dist: six (>=1.1)
Requires-Dist: wrapt (<2,>=1.10.10)
Provides-Extra: docs
Requires-Dist: sphinx (>=1.4.0); extra == 'docs'
Provides-Extra: test
Requires-Dist: bumpversion (==0.5.3); extra == 'test'
Requires-Dist: coverage (==.4.2); extra == 'test'
Requires-Dist: flake8 (==3.0.3); extra == 'test'
Requires-Dist: flake8-blind-except (==0.1.1); extra == 'test'
Requires-Dist: flake8-debugger (==1.4.0); extra == 'test'
Requires-Dist: isort (==4.2.5); extra == 'test'
Requires-Dist: pytest (==3.0.5); extra == 'test'
Requires-Dist: pytest-cov (==2.5.1); extra == 'test'
Requires-Dist: pytest-django (==3.1.2); extra == 'test'
